{"trial_id": "23", "hyperparameters": {"space": [{"class_name": "Int", "config": {"name": "units", "default": null, "conditions": [], "min_value": 50, "max_value": 150, "step": 10, "sampling": "linear"}}, {"class_name": "Choice", "config": {"name": "activation_h", "default": "linear", "conditions": [], "values": ["linear", "relu", "tanh"], "ordered": false}}, {"class_name": "Choice", "config": {"name": "learning_rate", "default": 0.01, "conditions": [], "values": [0.01, 0.001, 0.0001], "ordered": true}}], "values": {"units": 150, "activation_h": "relu", "learning_rate": 0.001}}, "metrics": {"metrics": {"loss": {"direction": "min", "observations": [{"value": [1.528391718864441], "step": 14}]}, "accuracy": {"direction": "max", "observations": [{"value": [0.42227083444595337], "step": 14}]}, "val_loss": {"direction": "min", "observations": [{"value": [1.4439224004745483], "step": 14}]}, "val_accuracy": {"direction": "max", "observations": [{"value": [0.4438333213329315], "step": 14}]}}}, "score": 0.4438333213329315, "best_step": 14, "status": "COMPLETED", "message": null}