{"trial_id": "07", "hyperparameters": {"space": [{"class_name": "Int", "config": {"name": "units", "default": null, "conditions": [], "min_value": 10, "max_value": 300, "step": 10, "sampling": "linear"}}, {"class_name": "Choice", "config": {"name": "activation_h", "default": "linear", "conditions": [], "values": ["linear", "relu"], "ordered": false}}, {"class_name": "Choice", "config": {"name": "activation_d", "default": "linear", "conditions": [], "values": ["linear", "relu", "tanh"], "ordered": false}}, {"class_name": "Choice", "config": {"name": "learning_rate", "default": 0.01, "conditions": [], "values": [0.01, 0.001, 0.0001], "ordered": true}}], "values": {"units": 80, "activation_h": "relu", "activation_d": "linear", "learning_rate": 0.01}}, "metrics": {"metrics": {"loss": {"direction": "min", "observations": [{"value": [0.004453959409147501], "step": 60}]}, "mean_squared_error": {"direction": "min", "observations": [{"value": [0.004453959409147501], "step": 60}]}, "val_loss": {"direction": "min", "observations": [{"value": [0.0044350032694637775], "step": 60}]}, "val_mean_squared_error": {"direction": "min", "observations": [{"value": [0.0044350032694637775], "step": 60}]}}}, "score": 0.0044350032694637775, "best_step": 60, "status": "COMPLETED", "message": null}